ajenti/__init__.py
ajenti/compat.py
ajenti/cookies.py
ajenti/core.py
ajenti/feedback.py
ajenti/http.py
ajenti/ipc.py
ajenti/licensing.py
ajenti/log.py
ajenti/middleware.py
ajenti/profiler.py
ajenti/routing.py
ajenti/users.py
ajenti/util.py
ajenti/api/__init__.py
ajenti/api/helpers.py
ajenti/api/http.py
ajenti/api/sensors.py
ajenti/locales/__init__.py
ajenti/locales/af_ZA/LC_MESSAGES/ajenti.mo
ajenti/locales/ar_SA/LC_MESSAGES/ajenti.mo
ajenti/locales/bg_BG/LC_MESSAGES/ajenti.mo
ajenti/locales/bn_BD/LC_MESSAGES/ajenti.mo
ajenti/locales/ca_ES/LC_MESSAGES/ajenti.mo
ajenti/locales/cs_CZ/LC_MESSAGES/ajenti.mo
ajenti/locales/da_DK/LC_MESSAGES/ajenti.mo
ajenti/locales/de_DE/LC_MESSAGES/ajenti.mo
ajenti/locales/el_GR/LC_MESSAGES/ajenti.mo
ajenti/locales/es_ES/LC_MESSAGES/ajenti.mo
ajenti/locales/et_EE/LC_MESSAGES/ajenti.mo
ajenti/locales/fa_IR/LC_MESSAGES/ajenti.mo
ajenti/locales/fi_FI/LC_MESSAGES/ajenti.mo
ajenti/locales/fr_FR/LC_MESSAGES/ajenti.mo
ajenti/locales/fy_NL/LC_MESSAGES/ajenti.mo
ajenti/locales/he_IL/LC_MESSAGES/ajenti.mo
ajenti/locales/hr_HR/LC_MESSAGES/ajenti.mo
ajenti/locales/hu_HU/LC_MESSAGES/ajenti.mo
ajenti/locales/id_ID/LC_MESSAGES/ajenti.mo
ajenti/locales/it_IT/LC_MESSAGES/ajenti.mo
ajenti/locales/ja_JP/LC_MESSAGES/ajenti.mo
ajenti/locales/ko_KR/LC_MESSAGES/ajenti.mo
ajenti/locales/lt_LT/LC_MESSAGES/ajenti.mo
ajenti/locales/lv_LV/LC_MESSAGES/ajenti.mo
ajenti/locales/my_MM/LC_MESSAGES/ajenti.mo
ajenti/locales/nl_NL/LC_MESSAGES/ajenti.mo
ajenti/locales/no_NO/LC_MESSAGES/ajenti.mo
ajenti/locales/pl_PL/LC_MESSAGES/ajenti.mo
ajenti/locales/pt_BR/LC_MESSAGES/ajenti.mo
ajenti/locales/pt_PT/LC_MESSAGES/ajenti.mo
ajenti/locales/ro_RO/LC_MESSAGES/ajenti.mo
ajenti/locales/ru_RU/LC_MESSAGES/ajenti.mo
ajenti/locales/sk_SK/LC_MESSAGES/ajenti.mo
ajenti/locales/sl_SI/LC_MESSAGES/ajenti.mo
ajenti/locales/sr_CS/LC_MESSAGES/ajenti.mo
ajenti/locales/sr_SP/LC_MESSAGES/ajenti.mo
ajenti/locales/sv_SE/LC_MESSAGES/ajenti.mo
ajenti-1.2.23.13.dist-info/DESCRIPTION.rst
ajenti-1.2.23.13.dist-info/METADATA
ajenti-1.2.23.13.dist-info/RECORD
ajenti-1.2.23.13.dist-info/WHEEL
ajenti-1.2.23.13.dist-info/metadata.json
ajenti-1.2.23.13.dist-info/top_level.txt
