Metadata-Version: 2.0
Name: ajenti
Version: 1.2.23.13
Summary: The server administration panel
Home-page: http://ajenti.org/
Author: Eugeny Pankov
Author-email: e@ajenti.org
License: UNKNOWN
Platform: UNKNOWN
Requires-Dist: gevent (==1.1b4)
Requires-Dist: gevent-socketio
Requires-Dist: gevent-websocket
Requires-Dist: lxml (>=2.2.4)
Requires-Dist: passlib
Requires-Dist: psutil (>=0.6.0)
Requires-Dist: python-catcher
Requires-Dist: python-daemon
Requires-Dist: python-exconsole (>=0.1.5)
Requires-Dist: python-ldap
Requires-Dist: requests (>=0.12.0)
Requires-Dist: reconfigure (>=0.1.43)
Requires-Dist: pyOpenSSL
Requires-Dist: Pillow
